MANIFEST.in
README.txt
setup.py
django_cms_simple_events.egg-info/PKG-INFO
django_cms_simple_events.egg-info/SOURCES.txt
django_cms_simple_events.egg-info/dependency_links.txt
django_cms_simple_events.egg-info/not-zip-safe
django_cms_simple_events.egg-info/requires.txt
django_cms_simple_events.egg-info/top_level.txt
simple_events/__init__.py
simple_events/admin.py
simple_events/cms_app.py
simple_events/cms_plugins.py
simple_events/models.py
simple_events/urls.py
simple_events/views.py
simple_events/locale/es/LC_MESSAGES/django.mo
simple_events/locale/es/LC_MESSAGES/django.po
simple_events/locale/gl/LC_MESSAGES/django.mo
simple_events/locale/gl/LC_MESSAGES/django.po
simple_events/templates/simple_events/event_detail.html
simple_events/templates/simple_events/events_archive.html
simple_events/templates/simple_events/events_calendar.html