Metadata-Version: 1.0
Name: django-cms-simple-events
Version: 0.4.1
Summary: A django-cms application for managing an events calendar.
Home-page: http://www.toporojo.es/
Author: Alejandro Núñez Liz
Author-email: alejandro@toporojo.es
License: BSD License
Platform: UNKNOWN
Classifier: Environment :: Web Environment
Classifier: Framework :: Django
Classifier: Intended Audience :: Developers
Classifier: License :: OSI Approved :: BSD License
Classifier: Operating System :: OS Independent
Classifier: Programming Language :: Python
Classifier: Programming Language :: Python :: 2.6
Classifier: Programming Language :: Python :: 2.7
Classifier: Topic :: Internet :: WWW/HTTP
Classifier: Topic :: Internet :: WWW/HTTP :: Dynamic Content
